cotality/__init__.py
cotality/app/__init__.py
cotality/app/base/__init__.py
cotality/app/base/base_app.py
cotality/app/base/clip_base_app.py
cotality/app/base/icons.py
cotality/app/base/resources/__init__.py
cotality/app/base/resources/static/images/logo.html
cotality/app/base/resources/static/images/logo.svg
cotality/app/base/resources/static/images/refresh.svg
cotality/app/base/resources/static/overlay.html
cotality/app/base/resources/static/style_panel.css
cotality/app/base/resources/static/style_streamlit.css
cotality/app/panel/__init__.py
cotality/app/panel/clip_app.py
cotality/app/panel/modules/__init__.py
cotality/app/panel/modules/dashboard.py
cotality/app/panel/modules/input.py
cotality/app/panel/modules/layout.py
cotality/app/panel/modules/secret.py
cotality/core/__init__.py
cotality/core/app_ids.py
cotality/core/clgxtyping.py
cotality/core/constants.py
cotality/core/decorator.py
cotality/core/error_codes.py
cotality/core/exception.py
cotality/core/interfaces/__init__.py
cotality/core/interfaces/database.py
cotality/core/interfaces/database_types.py
cotality/core/interfaces/secret.py
cotality/core/interfaces/sql_typing.py
cotality/core/interfaces/table.py
cotality/core/locale.py
cotality/core/locales/__init__.py
cotality/core/locales/en_US/LC_MESSAGES/base.mo
cotality/core/locales/en_US/LC_MESSAGES/base.po
cotality/core/locales/keys.py
cotality/core/logger.py
cotality/core/plaform_app_db.py
cotality/core/platform.py
cotality/core/utils/PROCESS_README.md
cotality/core/utils/PROCESS_STANDARDS_COMPLIANCE.md
cotality/core/utils/__init__.py
cotality/core/utils/dict.py
cotality/core/utils/misc.py
cotality/core/utils/process.py
cotality/core/utils/string.py
cotality/core/utils/system.py
cotality/core/utils/threads.py
cotality/local/__init__.py
cotality/local/snowflake/__init__.py
cotality/local/snowflake/database.py
cotality/platform/__init__.py
cotality/platform/bigquery/__init__.py
cotality/platform/bigquery/clip_app.py
cotality/platform/bigquery/database.py
cotality_awb_bigquery-0.0.12.dist-info/METADATA
cotality_awb_bigquery-0.0.12.dist-info/WHEEL
cotality_awb_bigquery-0.0.12.dist-info/RECORD
